{
  "schemaVersion": 1,
  "id": "noemotecraft-addon-flashback",
  "version": "0.1",
  "name": "NoEmotecraft Flashback Addon",
  "description": "NoEmotecraft and Flashback compatibility layer",
  "authors": [
    "KosmX",
    "ClaimGaming",
    "PavelDobCZ23"
  ],
  "contributors": [
    "TheMeko",
    "PavelDobCZ23"
  ],
  "contact": {
    "issues": "https://github.com/paveldobcz23/noemotecraft-flashback-addon/issues"
  },
  "icon": "emotecraft_flashback_addon_logo.png",
  "license": "MIT",
  "environment": "*",
  "entrypoints": {
    "client": [
      {
        "adapter": "kotlin",
        "value": "dev.kosmx.emotesCompatFlashback.rp.ClientInitKt::initializeClient"
      }
    ]
  },
  "depends": {
    "fabricloader": ">=0.16",
    "fabric": "*",
    "fabric-language-kotlin": ">=1.12.3+kotlin.2.0",
    "noemotecraft": ">=2.5.2",
    "flashback": "*",
    "minecraft": ">=1.21"
  }
}